easyboto-0.2.1.dist-info/metadata.json
easyboto-0.2.1.dist-info/METADATA
easyboto-0.2.1.dist-info/DESCRIPTION.rst
easyboto-0.2.1.dist-info/WHEEL
easyboto-0.2.1.dist-info/RECORD
easyboto-0.2.1.dist-info/top_level.txt
easyboto/__init__.py
