Metadata-Version: 2.0
Name: easyboto
Version: 0.2.1
Summary: Amazon Cloud made easy
Home-page: https://github.com/shantanuo/easyboto
Author: Shantanu Oak
Author-email: shantanu.oak@gmail.com
License: UNKNOWN
Platform: UNKNOWN
Requires-Dist: boto (>=1.0)
